tube_base/__init__.py
tube_base/interfaces.py
tube_base-0.0.1.dist-info/LICENSE
tube_base-0.0.1.dist-info/METADATA
tube_base-0.0.1.dist-info/WHEEL
tube_base-0.0.1.dist-info/top_level.txt
tube_base-0.0.1.dist-info/RECORD
