Metadata-Version: 2.1
Name: tube-base
Version: 0.0.1
Summary: Base of the tube box
Home-page: https://github.com/sixcodes/tube-base
Author: Jesué Junior
Author-email: opensource@sixcodes.com
License: MIT
Platform: UNKNOWN
Classifier: Programming Language :: Python :: 3.6
Classifier: Programming Language :: Python :: 3.7
Classifier: Programming Language :: Python :: 3.8
Classifier: Programming Language :: Python :: 3.9
